streamlit_plotly_mapbox_events/__init__.py
streamlit_plotly_mapbox_events/frontend/build/asset-manifest.json
streamlit_plotly_mapbox_events/frontend/build/bootstrap.min.css
streamlit_plotly_mapbox_events/frontend/build/index.html
streamlit_plotly_mapbox_events/frontend/build/static/js/main.18dc042f.js
streamlit_plotly_mapbox_events/frontend/build/static/js/main.18dc042f.js.LICENSE.txt
streamlit_plotly_mapbox_events/frontend/build/static/js/main.18dc042f.js.map
streamlit_plotly_mapbox_events-0.2.1.dist-info/licenses/LICENSE
streamlit_plotly_mapbox_events-0.2.1.dist-info/METADATA
streamlit_plotly_mapbox_events-0.2.1.dist-info/WHEEL
streamlit_plotly_mapbox_events-0.2.1.dist-info/top_level.txt
streamlit_plotly_mapbox_events-0.2.1.dist-info/RECORD
