Metadata-Version: 2.4
Name: streamlit_plotly_mapbox_events
Version: 0.2.1
Summary: A Streamlit component that integrates Plotly's interactive Mapbox visualizations, enabling bidirectional communication between the map and Streamlit. It allows for seamless rendering of Mapbox plots within Streamlit applications while supporting event handling, such as click, select, hover, and relayout events, to facilitate dynamic interactions and data updates.
Author: Reyemb
Author-email: info@reyemb.io
Requires-Python: >=3.6
License-File: LICENSE
Requires-Dist: streamlit>=1.45.0
Requires-Dist: plotly>=6.1.2
Dynamic: author
Dynamic: author-email
Dynamic: description
Dynamic: description-content-type
Dynamic: license-file
Dynamic: requires-dist
Dynamic: requires-python
Dynamic: summary
